plover_uinput_output/__init__.py
plover_uinput_output/set_xkb_alias.py
plover_uinput_output/subprocess_run.py
plover_uinput_output-0.0.3.dist-info/licenses/LICENSE
plover_uinput_output-0.0.3.dist-info/METADATA
plover_uinput_output-0.0.3.dist-info/WHEEL
plover_uinput_output-0.0.3.dist-info/entry_points.txt
plover_uinput_output-0.0.3.dist-info/top_level.txt
plover_uinput_output-0.0.3.dist-info/RECORD
