Metadata-Version: 2.4
Name: plover-uinput-output
Version: 0.0.3
Summary: Plover plugin to output with uinput (Linux systems) instead of xtest
Home-page: https://github.com/user202729/plover-uinput-output
Author: user202729
License: GNU General Public License v3 or later (GPLv3+)
Keywords: plover plover_plugin
Classifier: Environment :: Plugins
Classifier: License :: OSI Approved :: GNU General Public License v3 or later (GPLv3+)
Classifier: Operating System :: OS Independent
Classifier: Programming Language :: Python :: 3
License-File: LICENSE
Requires-Dist: plover>=4.0.0
Requires-Dist: python-uinput>=1.0.1
Dynamic: license-file
